{
  "rows": [
    {
      "id": 1,
      "customer": "John",
      "products": [
        {
          "name": "apple",
          "price": 200
        },
        {
          "name": "orange",
          "price": 100
        }
      ],
      "date": "2020-05-01"
    },
    {
      "id": 2,
      "customer": "rayhan",
      "products": [
        {
          "name": "tea",
          "price": 200
        }
      ],
      "date": "2020-03-01"
    },
    {
      "id": 3,
      "customer": "raju",
      "products": [
        {
          "name": "potato",
          "price": 200
        },
        {
          "name": "tomato",
          "price": 100
        }
      ],
      "date": "2020-02-04"
    },
    {
      "id": 4,
      "customer": "hello",
      "products": [
        {
          "name": "date",
          "price": 200
        },
        {
          "name": "grape",
          "price": 100
        }
      ],
      "date": "2020-07-02"
    },
    {
      "customer": "zzzzz",
      "products": [
        {
          "name": "applzzze",
          "price": 200
        },
        {
          "name": "oranzzzge",
          "price": 100
        }
      ],
      "date": "2020-05-01",
      "id": 5
    },
    {
      "customer": "zzzzz",
      "products": [
        {
          "name": "applzzze",
          "price": 200
        },
        {
          "name": "oranzzzge",
          "price": 100
        }
      ],
      "date": "2020-05-01",
      "id": 6
    },
    {
      "customer": "zzzzz",
      "products": [
        {
          "name": "applzzze",
          "price": 200
        },
        {
          "name": "oranzzzge",
          "price": 100
        }
      ],
      "date": "2020-05-01",
      "id": 7
    }
  ]
}
